malice/__init__.py
malice/apps.py
malice/tests.py
malice/urls.py
malice/views.py
django_malice-0.1.6.dist-info/LICENSE.txt
django_malice-0.1.6.dist-info/METADATA
django_malice-0.1.6.dist-info/WHEEL
django_malice-0.1.6.dist-info/top_level.txt
django_malice-0.1.6.dist-info/RECORD
