Metadata-Version: 2.1
Name: django-malice
Version: 0.1.6
Summary: A simple Django app that enables own occuring error.
Home-page: https://github.com/salexkidd/django_malice/
Author: salexkidd
Author-email: salexkidd@gmail.com
License: UNKNOWN
Keywords: django,testing
Platform: UNKNOWN
Classifier: Development Status :: 5 - Production/Stable
Classifier: Environment :: Web Environment
Classifier: Framework :: Django
Classifier: Intended Audience :: Developers
Classifier: License :: OSI Approved :: MIT License
Classifier: Operating System :: OS Independent
Classifier: Programming Language :: Python
Classifier: Programming Language :: Python :: 3
Classifier: Programming Language :: Python :: 3.6
Classifier: Programming Language :: Python :: 3.7
Classifier: Topic :: Internet :: WWW/HTTP
Classifier: Topic :: Internet :: WWW/HTTP :: Dynamic Content
